README.md
builtwith.py
setup.py
python_builtwith.egg-info/PKG-INFO
python_builtwith.egg-info/SOURCES.txt
python_builtwith.egg-info/dependency_links.txt
python_builtwith.egg-info/requires.txt
python_builtwith.egg-info/top_level.txt