Metadata-Version: 1.1
Name: python-builtwith
Version: 1.0.0
Summary: BuiltWith API versions 1, 2 and 7 client
Home-page: https://github.com/claymation/python-builtwith
Author: Clay McClure, Jon Gaulding, Andrew Harris
Author-email: clay@daemons.net
License: UNKNOWN
Platform: UNKNOWN
Classifier: Development Status :: 7 - Inactive
Classifier: Intended Audience :: Developers
Classifier: License :: OSI Approved :: MIT License
Classifier: Programming Language :: Python :: 2.7
Classifier: Programming Language :: Python :: 3.8
Classifier: Topic :: Internet :: WWW/HTTP
